pelican_data_loader/__init__.py
pelican_data_loader/api.py
pelican_data_loader/config.py
pelican_data_loader/data.py
pelican_data_loader/db.py
pelican_data_loader/utils.py
pelican_data_loader/external/person_api.py
pelican_data_loader-0.0.1.dist-info/METADATA
pelican_data_loader-0.0.1.dist-info/WHEEL
pelican_data_loader-0.0.1.dist-info/licenses/LICENSE
pelican_data_loader-0.0.1.dist-info/RECORD
