Metadata-Version: 2.4
Name: pelican-data-loader
Version: 0.0.1
Summary: Pelican Platform backed data loader
License-File: LICENSE
Requires-Python: >=3.12
Requires-Dist: beautifulsoup4>=4.13.4
Requires-Dist: datacite>=1.2.0
Requires-Dist: datasets>=3.6.0
Requires-Dist: fsspec>=2025.3.0
Requires-Dist: httpx>=0.28.1
Requires-Dist: minio>=7.2.15
Requires-Dist: mlcroissant>=1.0.17
Requires-Dist: pandas>=2.2.3
Requires-Dist: pelicanfs>=1.2.1
Requires-Dist: psycopg2-binary>=2.9.10
Requires-Dist: pydantic-settings>=2.10.1
Requires-Dist: pydantic>=2.11.4
Requires-Dist: python-dotenv>=1.1.0
Requires-Dist: s3fs>=2025.3.0
Requires-Dist: sqlmodel>=0.0.24
Requires-Dist: streamlit>=1.46.1
Provides-Extra: dev
Requires-Dist: ipykernel>=6.29.5; extra == 'dev'
Requires-Dist: torch>=2.7.1; extra == 'dev'
Requires-Dist: torchdata>=0.11.0; extra == 'dev'
